korrel8/__init__.py
korrel8/copier.py
korrel8/downloader.py
korrel8/uploader.py
test/__init__.py
test/test_uploader.py
korrel8_data_ingest-1.2.7.dist-info/METADATA
korrel8_data_ingest-1.2.7.dist-info/WHEEL
korrel8_data_ingest-1.2.7.dist-info/top_level.txt
korrel8_data_ingest-1.2.7.dist-info/RECORD
