Metadata-Version: 2.1
Name: korrel8-data-ingest
Version: 1.2.7
Summary: Korrel8 Library
Home-page: https://gitlab.com/k8ai
Author: Harichandan Pulagam
Author-email: hari@korrel8.ai
Project-URL: Bug Tracker, https://gitlab.com/k8ai/korrel8-pylibrary/-/issues
Project-URL: repository, https://gitlab.com/k8ai/korrel8-pylibrary
Classifier: Programming Language :: Python :: 3
Classifier: Operating System :: OS Independent
Requires-Python: >=3.7
Requires-Dist: boto3 (>=1.25.2)
